{
  "project_info": {
    "project_number": "54684655252",
    "project_id": "fir-mini-3e80b",
    "storage_bucket": "fir-mini-3e80b.appspot.com"
  },
  "client": [
    {
      "client_info": {
        "mobilesdk_app_id": "1:54684655252:android:1b9ab9a95f326b7dad9e81",
        "android_client_info": {
          "package_name": "id.ac.ukdw.miniprojectfirebase"
        }
      },
      "oauth_client": [
        {
          "client_id": "54684655252-fbkgpcbv6rlj15gub1enebusli3kcd8b.apps.googleusercontent.com",
          "client_type": 3
        }
      ],
      "api_key": [
        {
          "current_key": "AIzaSyAgacOEJX0X6CxaPWobx55ou7hafL09dHM"
        }
      ],
      "services": {
        "appinvite_service": {
          "other_platform_oauth_client": [
            {
              "client_id": "54684655252-fbkgpcbv6rlj15gub1enebusli3kcd8b.apps.googleusercontent.com",
              "client_type": 3
            }
          ]
        }
      }
    }
  ],
  "configuration_version": "1"
}